ds_pycontain/VERSION
ds_pycontain/__init__.py
ds_pycontain/__version__.py
ds_pycontain/docker_containers.py
ds_pycontain/py.typed
ds_pycontain/python_dockerized_repl.py
ds_pycontain/data/python_runner.py
ds_pycontain-0.0.3.dist-info/LICENSE
ds_pycontain-0.0.3.dist-info/METADATA
ds_pycontain-0.0.3.dist-info/WHEEL
ds_pycontain-0.0.3.dist-info/top_level.txt
ds_pycontain-0.0.3.dist-info/zip-safe
ds_pycontain-0.0.3.dist-info/RECORD
