Metadata-Version: 2.1
Name: ds-pycontain
Version: 0.0.3
Summary: deepsense.ai wrapper around docker python API
Author: deepsense.ai
Author-email: contact@deepsense.ai
License: MIT License (MIT)
Project-URL: "Homepage", https://deepsense-ai.github.io/ds-pycontain/
Project-URL: "Source Code", https://github.com/deepsense-ai/ds-pycontain/
Project-URL: "Bug Tracker", https://github.com/deepsense-ai/ds-pycontain/issues
Classifier: Development Status :: 3 - Alpha
Classifier: Intended Audience :: Developers
Classifier: Natural Language :: English
Classifier: License :: OSI Approved :: MIT License
Classifier: Operating System :: OS Independent
Classifier: Programming Language :: Python :: 3 :: Only
Classifier: Programming Language :: Python :: 3.8
Classifier: Programming Language :: Python :: 3.9
Classifier: Programming Language :: Python :: 3.10
Classifier: Programming Language :: Python :: 3.11
Classifier: Programming Language :: Python :: 3.12
Requires-Python: >=3.8
License-File: LICENSE
Requires-Dist: docker >=6.1.3
